setup.py
jenkins_jobs_travis/__init__.py
jenkins_jobs_travis/travis.py
jenkins_jobs_travis.egg-info/PKG-INFO
jenkins_jobs_travis.egg-info/SOURCES.txt
jenkins_jobs_travis.egg-info/dependency_links.txt
jenkins_jobs_travis.egg-info/entry_points.txt
jenkins_jobs_travis.egg-info/top_level.txt